{
    "tensorflow.python.distribute.values_util.write_object_proto": [],
    "tensorflow.python.distribute.values_util.get_on_write_saveable": [],
    "tensorflow.python.distribute.values_util.get_on_write_restore_ops": [],
    "tensorflow.python.distribute.values_util.get_on_read_saveable": [],
    "tensorflow.python.distribute.values_util.get_on_read_restore_ops": [],
    "tensorflow.python.distribute.values_util.in_replica_update_context": [],
    "tensorflow.python.distribute.values_util.on_write_assign": [],
    "tensorflow.python.distribute.values_util.on_write_assign_add": [],
    "tensorflow.python.distribute.values_util.on_write_assign_sub": [],
    "tensorflow.python.distribute.values_util.assign_on_each_device": [],
    "tensorflow.python.distribute.values_util.on_read_assign_sub_cross_replica": [],
    "tensorflow.python.distribute.values_util.on_read_assign_add_cross_replica": [],
    "tensorflow.python.distribute.values_util.on_read_assign_cross_replica": [],
    "tensorflow.python.distribute.values_util.scatter_sub": [],
    "tensorflow.python.distribute.values_util.scatter_add": [],
    "tensorflow.python.distribute.values_util.scatter_mul": [],
    "tensorflow.python.distribute.values_util.scatter_div": [],
    "tensorflow.python.distribute.values_util.scatter_min": [],
    "tensorflow.python.distribute.values_util.scatter_max": [],
    "tensorflow.python.distribute.values_util.scatter_update": [],
    "tensorflow.python.distribute.values_util.get_current_replica_id_as_int": [],
    "tensorflow.python.distribute.values_util.assign_on_device": [],
    "tensorflow.python.distribute.values_util.assign_add_on_device": [],
    "tensorflow.python.distribute.values_util.assign_sub_on_device": [],
    "tensorflow.python.distribute.values_util.assert_replica_context": [],
    "tensorflow.python.distribute.values_util.apply_aggregation": [],
    "tensorflow.python.distribute.values_util.is_saving_non_distributed": [],
    "tensorflow.python.distribute.values_util.mark_as_unsaveable": []
}