{
    "keras.saving.saved_model.load_context.load_context": [],
    "keras.saving.saved_model.load_context.get_load_options": [],
    "keras.saving.saved_model.load_context.in_load_context": [],
    "keras.saving.saved_model.load_context.LoadContext.__init__": [],
    "keras.saving.saved_model.load_context.LoadContext.set_load_options": [],
    "keras.saving.saved_model.load_context.LoadContext.clear_load_options": [],
    "keras.saving.saved_model.load_context.LoadContext.load_options": [],
    "keras.saving.saved_model.load_context.LoadContext.in_load_context": [],
    "keras.saving.saved_model.load_context.LoadContext": []
}