{
    "keras.saving.saved_model.load.load": [],
    "keras.saving.saved_model.load._read_legacy_metadata": [],
    "keras.saving.saved_model.load._generate_object_paths": [],
    "keras.saving.saved_model.load._is_graph_network": [],
    "keras.saving.saved_model.load._finalize_saved_model_layers": [],
    "keras.saving.saved_model.load._unable_to_call_layer_due_to_serialization_issue": [],
    "keras.saving.saved_model.load._finalize_config_layers": [],
    "keras.saving.saved_model.load._finalize_metric": [],
    "keras.saving.saved_model.load._restore_layer_unconditional_losses": [],
    "keras.saving.saved_model.load._restore_layer_activation_loss": [],
    "keras.saving.saved_model.load.revive_custom_object": [],
    "keras.saving.saved_model.load._restore_layer_metrics": [],
    "keras.saving.saved_model.load._revive_setter": [],
    "keras.saving.saved_model.load.recursively_deserialize_keras_object": [],
    "keras.saving.saved_model.load.get_common_shape": [],
    "keras.saving.saved_model.load.infer_inputs_from_restored_call_function": [],
    "keras.saving.saved_model.load._set_network_attributes_from_metadata": [],
    "keras.saving.saved_model.load._maybe_add_serialized_attributes": [],
    "keras.saving.saved_model.load._get_keras_attr": [],
    "keras.saving.saved_model.load.KerasObjectLoader.__init__": [],
    "keras.saving.saved_model.load.KerasObjectLoader.del_tracking": [],
    "keras.saving.saved_model.load.KerasObjectLoader._add_children_recreated_from_config": [],
    "keras.saving.saved_model.load.KerasObjectLoader.load_layers": [],
    "keras.saving.saved_model.load.KerasObjectLoader._load_layer": [],
    "keras.saving.saved_model.load.KerasObjectLoader._revive_from_config": [],
    "keras.saving.saved_model.load.KerasObjectLoader._revive_graph_network": [],
    "keras.saving.saved_model.load.KerasObjectLoader._revive_layer_or_model_from_config": [],
    "keras.saving.saved_model.load.KerasObjectLoader._revive_metric_from_config": [],
    "keras.saving.saved_model.load.KerasObjectLoader._try_build_layer": [],
    "keras.saving.saved_model.load.KerasObjectLoader._load_edges": [],
    "keras.saving.saved_model.load.KerasObjectLoader.get_path": [],
    "keras.saving.saved_model.load.KerasObjectLoader.finalize_objects": [],
    "keras.saving.saved_model.load.KerasObjectLoader._unblock_model_reconstruction": [],
    "keras.saving.saved_model.load.KerasObjectLoader._reconstruct_all_models": [],
    "keras.saving.saved_model.load.KerasObjectLoader._reconstruct_model": [],
    "keras.saving.saved_model.load.KerasObjectLoader._get_child_layer_node_ids": [],
    "keras.saving.saved_model.load.KerasObjectLoader._search_for_child_node": [],
    "keras.saving.saved_model.load.KerasObjectLoader._infer_inputs": [],
    "keras.saving.saved_model.load.KerasObjectLoader._config_node_setter": [],
    "keras.saving.saved_model.load.RevivedLayer._init_from_metadata": [],
    "keras.saving.saved_model.load.RevivedLayer.keras_api": [],
    "keras.saving.saved_model.load.RevivedLayer.get_config": [],
    "keras.saving.saved_model.load.RevivedInputLayer._init_from_metadata": [],
    "keras.saving.saved_model.load.RevivedInputLayer.get_config": [],
    "keras.saving.saved_model.load.RevivedNetwork._init_from_metadata": [],
    "keras.saving.saved_model.load.KerasObjectLoader": [],
    "keras.saving.saved_model.load.RevivedLayer": [],
    "keras.saving.saved_model.load.RevivedInputLayer": [],
    "keras.saving.saved_model.load.RevivedNetwork": []
}