{
    "statsmodels.base.data._asarray_2dcolumns": [],
    "statsmodels.base.data._asarray_2d_null_rows": [],
    "statsmodels.base.data._nan_rows": [],
    "statsmodels.base.data._make_endog_names": [],
    "statsmodels.base.data._make_exog_names": [],
    "statsmodels.base.data.handle_missing": [],
    "statsmodels.base.data.handle_data_class_factory": [],
    "statsmodels.base.data.handle_data": [],
    "statsmodels.base.data.ModelData.__init__": [],
    "statsmodels.base.data.ModelData.__getstate__": [],
    "statsmodels.base.data.ModelData.__setstate__": [],
    "statsmodels.base.data.ModelData._handle_constant": [],
    "statsmodels.base.data.ModelData._drop_nans": [],
    "statsmodels.base.data.ModelData._drop_nans_2d": [],
    "statsmodels.base.data.ModelData.handle_missing": [],
    "statsmodels.base.data.ModelData._convert_endog_exog": [],
    "statsmodels.base.data.ModelData.ynames": [],
    "statsmodels.base.data.ModelData.xnames": [],
    "statsmodels.base.data.ModelData.param_names": [],
    "statsmodels.base.data.ModelData.cov_names": [],
    "statsmodels.base.data.ModelData.row_labels": [],
    "statsmodels.base.data.ModelData._get_row_labels": [],
    "statsmodels.base.data.ModelData._get_names": [],
    "statsmodels.base.data.ModelData._get_yarr": [],
    "statsmodels.base.data.ModelData._get_xarr": [],
    "statsmodels.base.data.ModelData._check_integrity": [],
    "statsmodels.base.data.ModelData.wrap_output": [],
    "statsmodels.base.data.ModelData.attach_columns": [],
    "statsmodels.base.data.ModelData.attach_columns_eq": [],
    "statsmodels.base.data.ModelData.attach_cov": [],
    "statsmodels.base.data.ModelData.attach_cov_eq": [],
    "statsmodels.base.data.ModelData.attach_rows": [],
    "statsmodels.base.data.ModelData.attach_dates": [],
    "statsmodels.base.data.ModelData.attach_mv_confint": [],
    "statsmodels.base.data.ModelData.attach_generic_columns": [],
    "statsmodels.base.data.ModelData.attach_generic_columns_2d": [],
    "statsmodels.base.data.ModelData.attach_ynames": [],
    "statsmodels.base.data.PatsyData._get_names": [],
    "statsmodels.base.data.PandasData._convert_endog_exog": [],
    "statsmodels.base.data.PandasData._drop_nans": [],
    "statsmodels.base.data.PandasData._drop_nans_2d": [],
    "statsmodels.base.data.PandasData._check_integrity": [],
    "statsmodels.base.data.PandasData._get_row_labels": [],
    "statsmodels.base.data.PandasData.attach_generic_columns": [],
    "statsmodels.base.data.PandasData.attach_generic_columns_2d": [],
    "statsmodels.base.data.PandasData.attach_columns": [],
    "statsmodels.base.data.PandasData.attach_columns_eq": [],
    "statsmodels.base.data.PandasData.attach_cov": [],
    "statsmodels.base.data.PandasData.attach_cov_eq": [],
    "statsmodels.base.data.PandasData.attach_rows": [],
    "statsmodels.base.data.PandasData.attach_dates": [],
    "statsmodels.base.data.PandasData.attach_mv_confint": [],
    "statsmodels.base.data.PandasData.attach_ynames": [],
    "statsmodels.base.data.ModelData": [],
    "statsmodels.base.data.PatsyData": [],
    "statsmodels.base.data.PandasData": []
}